LocationByIP/__init__.py
locationbyip-0.4.dist-info/METADATA
locationbyip-0.4.dist-info/WHEEL
locationbyip-0.4.dist-info/top_level.txt
locationbyip-0.4.dist-info/RECORD
