Metadata-Version: 2.1
Name: locationbyip
Version: 0.4
Summary: By this package you can find location, coordinates, isp details to use in your application.
Home-page: UNKNOWN
Author: Awais khan
Author-email: contact@awaiskhan.com.pk
License: UNKNOWN
Platform: UNKNOWN
Requires-Dist: requests
